{
  "collectionName": "components_index_page_carousel_index_pages",
  "info": {
    "displayName": "Carousel Index Page",
    "icon": "picture",
    "description": ""
  },
  "options": {},
  "attributes": {
    "title": {
      "type": "string",
      "required": true
    },
    "subTitle": {
      "type": "text"
    },
    "url": {
      "type": "text"
    },
    "background": {
      "type": "media",
      "multiple": false,
      "required": true,
      "allowedTypes": [
        "images"
      ]
    },
    "buttonText": {
      "type": "string",
      "required": false
    },
    "img": {
      "type": "media",
      "multiple": false,
      "required": false,
      "allowedTypes": [
        "images"
      ]
    }
  }
}
